<?xml version="1.0" encoding="UTF-8"?>
<!--  Copyright (c) 2020, NXP.
      All rights reserved.

 Redistribution and use in source and binary forms, with or without modification,
 are permitted provided that the following conditions are met:

 Redistributions of source code must retain the above copyright notice, this list
 of conditions and the following disclaimer.

 Redistributions in binary form must reproduce the above copyright notice, this
 list of conditions and the following disclaimer in the documentation and/or
 other materials provided with the distribution.

 Neither the name of NXP, Inc. nor the names of its
 contributors may be used to endorse or promote products derived from this
 software without specific prior written permission.

 THIS SOFTWARE IS PROVIDED BY THE COPYRIGHT HOLDERS AND CONTRIBUTORS "AS IS" AND
 ANY EXPRESS OR IMPLIED WARRANTIES, INCLUDING, BUT NOT LIMITED TO, THE IMPLIED
 WARRANTIES OF MERCHANTABILITY AND FITNESS FOR A PARTICULAR PURPOSE ARE
 DISCLAIMED. IN NO EVENT SHALL THE COPYRIGHT HOLDER OR CONTRIBUTORS BE LIABLE FOR
 ANY DIRECT, INDIRECT, INCIDENTAL, SPECIAL, EXEMPLARY, OR CONSEQUENTIAL DAMAGES
 (INCLUDING, BUT NOT LIMITED TO, PROCUREMENT OF SUBSTITUTE GOODS OR SERVICES;
 LOSS OF USE, DATA, OR PROFITS; OR BUSINESS INTERRUPTION) HOWEVER CAUSED AND ON
 ANY THEORY OF LIABILITY, WHETHER IN CONTRACT, STRICT LIABILITY, OR TORT
 (INCLUDING NEGLIGENCE OR OTHERWISE) ARISING IN ANY WAY OUT OF THE USE OF THIS
 SOFTWARE, EVEN IF ADVISED OF THE POSSIBILITY OF SUCH DAMAGE.   -->

<!DOCTYPE target SYSTEM "gdb-target.dtd">
<feature name="spt3-special-regs">
    <reg bitsize="64" name="spr0" type="uint64" />
    <reg bitsize="64" name="spr1" type="uint64" />
    <reg bitsize="64" name="spr2" type="uint64" />
    <reg bitsize="64" name="spr3" type="uint64" />
    <reg bitsize="64" name="spr4" type="uint64" />
    <reg bitsize="64" name="spr5" type="uint64" />
    <reg bitsize="64" name="spr6" type="uint64" />
    <reg bitsize="64" name="spr7" type="uint64" />
    <reg bitsize="64" name="spr8" type="uint64" />
    <reg bitsize="64" name="spr9" type="uint64" />
    <reg bitsize="64" name="hw_spr0" type="uint64" />
    <reg bitsize="64" name="hw_spr1" type="uint64" />
    <reg bitsize="64" name="hw_spr2" type="uint64" />
    <reg bitsize="64" name="hw_spr3" type="uint64" />
    <reg bitsize="64" name="hw_spr4" type="uint64" />
    <reg bitsize="64" name="hw_spr5" type="uint64" />
    <reg bitsize="64" name="evt_spr0" type="uint64" />
    <reg bitsize="64" name="evt_spr1" type="uint64" />
    <reg bitsize="64" name="evt_spr2" type="uint64" />
    <reg bitsize="64" name="evt_spr3" type="uint64" />
    <reg bitsize="64" name="evt_spr4" type="uint64" />
    <reg bitsize="64" name="evt_spr5" type="uint64" />
    <reg bitsize="64" name="evt_spr6" type="uint64" />
    <reg bitsize="64" name="evt_spr7" type="uint64" />
    <reg bitsize="64" name="evt_spr8" type="uint64" />
    <reg bitsize="64" name="evt_spr9" type="uint64" />
    <reg bitsize="64" name="chrp_spr0" type="uint64" />
    <reg bitsize="64" name="chrp_spr1" type="uint64" />
    <reg bitsize="64" name="chrp_spr2" type="uint64" />
    <reg bitsize="64" name="chrp_spr3" type="uint64" />
    <reg bitsize="64" name="chrp_spr4" type="uint64" />
    <reg bitsize="64" name="chrp_spr5" type="uint64" />
    <reg bitsize="64" name="chrp_spr6" type="uint64" />
    <reg bitsize="64" name="chrp_spr7" type="uint64" />
</feature>
